MANIFEST.in
setup.py
django_floppy_gumby.egg-info/PKG-INFO
django_floppy_gumby.egg-info/SOURCES.txt
django_floppy_gumby.egg-info/dependency_links.txt
django_floppy_gumby.egg-info/requires.txt
django_floppy_gumby.egg-info/top_level.txt
floppy_gumby_forms/__init__.py
floppy_gumby_forms/templates/floppy_gumby_forms/input.html
floppy_gumby_forms/templates/floppy_gumby_forms/select.html
floppy_gumby_forms/templates/floppy_gumby_forms/layouts/gumby.html
floppy_gumby_forms/templates/floppy_gumby_forms/rows/gumby.html