Metadata-Version: 1.1
Name: django-floppy-gumby
Version: 0.1
Summary: Gumby Framework forms for Django using floppy forms. A floppy and gumby project.
Home-page: https://github.com/burke-software/django-floppy-gumby
Author: David Burke
Author-email: david@burkesoftware.com
License: BSD
Keywords: django gumby
Platform: UNKNOWN
Classifier: Development Status :: 4 - Beta
Classifier: Environment :: Web Environment
Classifier: Framework :: Django
Classifier: Programming Language :: Python
Classifier: Intended Audience :: Developers
Classifier: License :: OSI Approved :: BSD License
